.gitignore
aau_gomapedge_etl-0.4.1.dist-info/METADATA
aau_gomapedge_etl-0.4.1.dist-info/WHEEL
aau_gomapedge_etl/__init__.py
aau_gomapedge_etl/__sql/extract.sql
aau_gomapedge_etl/__sql/load_fact_detection.sql
aau_gomapedge_etl/__sql/load_fact_gps.sql
aau_gomapedge_etl/__sql/transform.sql
aau_gomapedge_etl/clustering/__init__.py
aau_gomapedge_etl/clustering/angle_balancing_dbscan.py
aau_gomapedge_etl/clustering/ecadbscan/ecadbscan.c
aau_gomapedge_etl/clustering/ecadbscan/ecadbscan.cpython-311-x86_64-linux-gnu.so
aau_gomapedge_etl/clustering/ecadbscan/ecadbscan.cpython-312-x86_64-linux-gnu.so
aau_gomapedge_etl/clustering/ecadbscan/ecadbscan.pyi
aau_gomapedge_etl/clustering/ecadbscan/ecadbscan.pyx
aau_gomapedge_etl/clustering/weighted_directional_dbscan.py
aau_gomapedge_etl/dimensions/__init__.py
aau_gomapedge_etl/dimensions/base_dim.py
aau_gomapedge_etl/dimensions/dim_address.py
aau_gomapedge_etl/dimensions/dim_aggregator.py
aau_gomapedge_etl/dimensions/dim_cls.py
aau_gomapedge_etl/dimensions/dim_data_loader.py
aau_gomapedge_etl/dimensions/dim_date.py
aau_gomapedge_etl/dimensions/dim_grouper.py
aau_gomapedge_etl/dimensions/dim_model.py
aau_gomapedge_etl/dimensions/dim_obj_img.py
aau_gomapedge_etl/dimensions/dim_postprocessor.py
aau_gomapedge_etl/dimensions/dim_preprocess.py
aau_gomapedge_etl/dimensions/dim_time.py
aau_gomapedge_etl/dimensions/dim_trip.py
aau_gomapedge_etl/dimensions/dim_user.py
aau_gomapedge_etl/extract/__init__.py
aau_gomapedge_etl/extract/detection.py
aau_gomapedge_etl/extract/upload/_addresses.py
aau_gomapedge_etl/extract/upload/_classification.py
aau_gomapedge_etl/extract/upload/_detections.py
aau_gomapedge_etl/extract/upload/_map_matching.py
aau_gomapedge_etl/extract/upload/upload_extractor.py
aau_gomapedge_etl/load/__common.py
aau_gomapedge_etl/load/fact_detection.py
aau_gomapedge_etl/load/fact_detection_agg.py
aau_gomapedge_etl/load/fact_gps.py
aau_gomapedge_etl/model/__init__.py
aau_gomapedge_etl/model/db_types.py
aau_gomapedge_etl/model/filesystem_user_sequence.py
aau_gomapedge_etl/model/osrm.py
aau_gomapedge_etl-0.4.1.dist-info/RECORD
