Metadata-Version: 2.1
Name: aau-gomapedge-etl
Version: 0.4.1
Summary: This is the GoMap Edge ETL workflow package
Author-Email: Kasper Fromm Pedersen <kasperfromm@protonmail.com>, Kristian Torp <torp@cs.aau.dk>
License: MIT
Requires-Python: <3.13,>=3.10
Requires-Dist: simpleetl==1.1.*
Requires-Dist: geopy==2.4.*
Requires-Dist: user-agents==2.2.*
Requires-Dist: pydantic-settings==2.2.*
Requires-Dist: geojson-pydantic==1.1.*
Requires-Dist: requests==2.31.*
Requires-Dist: yolonnx==0.1.*
Requires-Dist: onnxruntime-gpu==1.17.*
Requires-Dist: duckdb==1.0.*
Requires-Dist: polars[pyarrow]==0.20.*
Requires-Dist: scikit-learn==1.4.*
